perigon_sdk/__init__.py
perigon_sdk/api/__init__.py
perigon_sdk/api/natural_language_api.py
perigon_sdk/api/news_stories_api.py
perigon_sdk/api/supplemental_endpoints_api.py
perigon_sdk/api/v1_api.py
perigon_sdk/api_client.py
perigon_sdk/api_response.py
perigon_sdk/exceptions.py
perigon_sdk/models/__init__.py
perigon_sdk/models/article.py
perigon_sdk/models/article_search_filter.py
perigon_sdk/models/article_search_params.py
perigon_sdk/models/auth_exception.py
perigon_sdk/models/auth_exception_cause.py
perigon_sdk/models/auth_exception_cause_stack_trace_inner.py
perigon_sdk/models/category_holder.py
perigon_sdk/models/category_with_score_holder.py
perigon_sdk/models/company_count.py
perigon_sdk/models/company_holder.py
perigon_sdk/models/coordinate.py
perigon_sdk/models/coordinate_filter.py
perigon_sdk/models/entity_holder.py
perigon_sdk/models/event_type_holder.py
perigon_sdk/models/id_name_holder.py
perigon_sdk/models/illegal_parameter_exception.py
perigon_sdk/models/internal_error_exception.py
perigon_sdk/models/journalist.py
perigon_sdk/models/key_point.py
perigon_sdk/models/keyword_holder.py
perigon_sdk/models/label_holder.py
perigon_sdk/models/location_count.py
perigon_sdk/models/location_holder.py
perigon_sdk/models/name_count.py
perigon_sdk/models/news_cluster.py
perigon_sdk/models/not_found_exception.py
perigon_sdk/models/person_count.py
perigon_sdk/models/person_holder.py
perigon_sdk/models/place.py
perigon_sdk/models/query_search_result.py
perigon_sdk/models/question.py
perigon_sdk/models/record_stat_holder.py
perigon_sdk/models/search_result.py
perigon_sdk/models/sentiment_holder.py
perigon_sdk/models/source_holder.py
perigon_sdk/models/source_location.py
perigon_sdk/models/standard_search_result.py
perigon_sdk/models/table_search_result.py
perigon_sdk/models/too_many_requests_exception.py
perigon_sdk/models/topic_holder.py
perigon_sdk/py.typed
perigon_sdk-0.5.0.dist-info/METADATA
perigon_sdk-0.5.0.dist-info/WHEEL
perigon_sdk-0.5.0.dist-info/RECORD
